Metadata-Version: 2.1
Name: br-loterias
Version: 0.0.4
Summary: br loterias api
Home-page: https://github.com/lucianovilasboas/br_loterias
Author: Luciano Vilas Boas Espiridião
Author-email: lucianovilasboas@gmail.com
License: MIT
Keywords: loterias brazil
Platform: UNKNOWN
Classifier: Programming Language :: Python :: 3
Classifier: License :: OSI Approved :: MIT License
Classifier: Operating System :: OS Independent
Requires-Python: >=3.0
